pymediainfo/MediaInfo.dll
pymediainfo/__init__.py
pymediainfo_tensoraws-6.1.0.dist-info/METADATA
pymediainfo_tensoraws-6.1.0.dist-info/WHEEL
pymediainfo_tensoraws-6.1.0.dist-info/entry_points.txt
pymediainfo_tensoraws-6.1.0.dist-info/licenses/LICENSE
pymediainfo_tensoraws-6.1.0.dist-info/RECORD
