Metadata-Version: 2.1
Name: pymediainfo-tensoraws
Version: 6.1.0
Author-Email: Tohrusky <65994850+Tohrusky@users.noreply.github.com>
License: MIT
Classifier: Development Status :: 5 - Production/Stable
Classifier: Programming Language :: Python :: 3.8
Classifier: Programming Language :: Python :: 3.9
Classifier: Programming Language :: Python :: 3.10
Classifier: Programming Language :: Python :: 3.11
Classifier: Programming Language :: Python :: 3.12
Classifier: Programming Language :: Python :: 3.13
Classifier: Programming Language :: Python :: 3 :: Only
Classifier: Programming Language :: Python :: Implementation :: CPython
Classifier: Programming Language :: Python :: Implementation :: PyPy
Classifier: Operating System :: POSIX :: Linux
Classifier: Operating System :: MacOS :: MacOS X
Classifier: Operating System :: Microsoft :: Windows
Classifier: License :: OSI Approved :: MIT License
Project-URL: Homepage, https://github.com/TensoRaws/pymediainfo-tensoraws
Project-URL: Repository, https://github.com/TensoRaws/pymediainfo-tensoraws
Requires-Python: >=3.8
